[
  {
    "id": "real_yield",
    "value": 2.21,
    "z": 1.7134557898013203,
    "desc": "10-year TIPS real yield; rising real yields pressure growth and long-duration assets."
  },
  {
    "id": "breakeven",
    "value": 2.33,
    "z": 0.2410229790380841,
    "desc": "10-year inflation breakeven; higher breakevens imply rising inflation expectations."
  },
  {
    "id": "usd",
    "value": 120.0831,
    "z": -0.7188292672921517,
    "desc": "Trade-weighted USD (broad); a stronger dollar can be a headwind for risk assets and commodities."
  },
  {
    "id": "hy_oas",
    "value": 2.75,
    "z": -0.8381244753693062,
    "desc": "High-yield credit option-adjusted spread; widening spreads suggest stress in credit markets."
  },
  {
    "id": "ig_oas",
    "value": 0.75,
    "z": -1.1461880910148226,
    "desc": "Investment-grade credit spread; widening indicates risk aversion and tightening conditions."
  },
  {
    "id": "net_liquidity",
    "value": -869003567000000.0,
    "z": -0.8580725045478723,
    "desc": "Net liquidity = Fed balance sheet minus reverse repo and Treasury cash; rising liquidity supports risk assets."
  },
  {
    "id": "claims",
    "value": 225000.0,
    "z": 0.10880880189716381,
    "desc": "Weekly initial unemployment claims; rising claims may signal labor market weakness."
  },
  {
    "id": "spx_rsi14",
    "value": 52.82615389879221,
    "z": -0.2966383277896263,
    "desc": "S&P 500 RSI (14-day); measures momentum; overbought >70, oversold <30."
  },
  {
    "id": "vix_level",
    "value": 18.92,
    "z": 0.10167300775702509,
    "desc": "CBOE Volatility Index (VIX); higher levels signal market stress."
  },
  {
    "id": "vix_term",
    "value": -1.8699999999999974,
    "z": -0.0265489705347587,
    "desc": "VIX term structure (VIX minus VIX3M); positive spread indicates backwardation (stress)."
  }
]